prophet/__init__.py
prophet/diagnostics.py
prophet/forecaster.py
prophet/hdays.py
prophet/make_holidays.py
prophet/models.py
prophet/plot.py
prophet/serialize.py
prophet/utilities.py
prophet_nogpl-1.0.2.dist-info/LICENSE
prophet_nogpl-1.0.2.dist-info/WHEEL
prophet_nogpl-1.0.2.dist-info/METADATA
prophet_nogpl-1.0.2.dist-info/RECORD
