Metadata-Version: 2.1
Name: prophet-nogpl
Version: 1.0.2
Summary: 
Home-page: https://github.com/lucidfrontier45/prophet-nogpl
License: MIT
Author: Du Shiqiao
Author-email: lucidfrontier.45@gmail.com
Requires-Python: >=3.8,<4
Classifier: License :: OSI Approved :: MIT License
Classifier: Programming Language :: Python :: 3
Classifier: Programming Language :: Python :: 3.10
Classifier: Programming Language :: Python :: 3.7
Classifier: Programming Language :: Python :: 3.8
Classifier: Programming Language :: Python :: 3.9
Requires-Dist: LunarCalendar (>=0.0.9,<0.0.10)
Requires-Dist: cmdstanpy (>=1.0.1,<2.0.0)
Requires-Dist: convertdate (>=2.4.0,<3.0.0)
Requires-Dist: holidays (>=0.13,<0.14)
Requires-Dist: matplotlib (>=3.5.1,<4.0.0)
Requires-Dist: pandas (>=1.4.1,<2.0.0)
Requires-Dist: python-dateutil (>=2.8.2,<3.0.0)
Requires-Dist: requests (>=2.27.1,<3.0.0)
Requires-Dist: tqdm (>=4.63.0,<5.0.0)
Project-URL: Repository, https://github.com/lucidfrontier45/prophet-nogpl
